tahini/__init__.py
tahini/meta.py
tahini/core/__init__.py
tahini/core/base.py
tahini/core/edges.py
tahini/core/graph.py
tahini/core/nodes.py
tahini/plot/__init__.py
tahini/plot/engine.py
tahini/plot/positions.py
tahini/testing/__init__.py
tahini/testing/testing.py
tests/test_core/__init__.py
tests/test_core/test_base.py
tests/test_core/test_edges.py
tests/test_core/test_graph.py
tests/test_core/test_nodes.py
tests/test_plot/__init__.py
tests/test_plot/test_engine.py
tests/test_plot/test_positions.py
tests/test_testing/__init__.py
tests/test_testing/test_testing.py
tahini-2021.3.1.dist-info/LICENSE
tahini-2021.3.1.dist-info/METADATA
tahini-2021.3.1.dist-info/WHEEL
tahini-2021.3.1.dist-info/top_level.txt
tahini-2021.3.1.dist-info/RECORD
