Metadata-Version: 2.1
Name: tahini
Version: 2021.3.1
Summary: Python package for graph theory
Home-page: https://github.com/tahini-dev/tahini
Author: tahini-dev
Author-email: tahini.dev@gmail.com
License: UNKNOWN
Platform: UNKNOWN
Requires-Python: >=3.7
Requires-Dist: pandas
Requires-Dist: numpy
Provides-Extra: all
Requires-Dist: plotly ; extra == 'all'
Provides-Extra: plotly
Requires-Dist: plotly ; extra == 'plotly'
